dataset_librarian/__init__.py
dataset_librarian/dataset.py
dataset_librarian/datasets_urls.json
dataset_librarian/terms_and_conditions.txt
dataset_librarian/dataset_api/__init__.py
dataset_librarian/dataset_api/download.py
dataset_librarian/dataset_api/preprocess.py
dataset_librarian/scripts/__init__.py
dataset_librarian/scripts/brca/__init__.py
dataset_librarian/scripts/brca/create_data_split.py
dataset_librarian/scripts/brca/prepare_nlp_data.py
dataset_librarian/scripts/brca/prepare_vision_data.py
dataset_librarian/scripts/mvtec-ad/__init__.py
dataset_librarian/scripts/mvtec-ad/csv_generator_mvtec.py
dataset_librarian-1.0.4.dist-info/METADATA
dataset_librarian-1.0.4.dist-info/WHEEL
dataset_librarian-1.0.4.dist-info/top_level.txt
dataset_librarian-1.0.4.dist-info/RECORD
