Metadata-Version: 2.1
Name: dataset-librarian
Version: 1.0.4
Summary: Dataset librarian is a tool to download and apply the preprocessing needed for the list of supported datasets
Author-email: IntelAI <IntelAI@intel.com>
Classifier: License :: OSI Approved :: Apache Software License
Classifier: Programming Language :: Python :: 3
Classifier: Programming Language :: Python :: 3.9
Classifier: Programming Language :: Python :: 3.10
Classifier: Operating System :: OS Independent
Requires-Python: <3.11,>=3.9
Requires-Dist: pandas
Requires-Dist: tqdm
Requires-Dist: docx2txt
Requires-Dist: openpyxl
Requires-Dist: pillow
Requires-Dist: scikit-learn-intelex
Requires-Dist: python-dotenv
Requires-Dist: wget
